hebra/__init__.py
hebra/sdk.py
hebra/bin/.gitkeep
hebra/bin/core
hebra/lib/__init__.py
hebra/lib/service_connection.py
hebra/lib/utils.py
hebra/proto/common/v1/common.proto
hebra/proto/common/v1/common_pb2.py
hebra/proto/common/v1/common_pb2.pyi
hebra/proto/core/collector/v1/collector_service.proto
hebra/proto/core/collector/v1/collector_service_pb2.py
hebra/proto/core/collector/v1/collector_service_pb2.pyi
hebra/proto/core/collector/v1/collector_service_pb2_grpc.py
hebra/proto/core/health/v1/health_service.proto
hebra/proto/core/lifecycle/__init__.py
hebra/proto/core/lifecycle/v1/__init__.py
hebra/proto/core/lifecycle/v1/lifecycle_service.proto
hebra/proto/core/lifecycle/v1/lifecycle_service_pb2.py
hebra/proto/core/lifecycle/v1/lifecycle_service_pb2.pyi
hebra/proto/core/lifecycle/v1/lifecycle_service_pb2_grpc.py
hebra/proto/record/v1/record.proto
hebra/proto/record/v1/record_pb2.py
hebra/proto/record/v1/record_pb2.pyi
hebra/run/__init__.py
hebra/run/main.py
hebra/run/state.py
hebra-0.1.0.dist-info/METADATA
hebra-0.1.0.dist-info/WHEEL
hebra-0.1.0.dist-info/RECORD
