Metadata-Version: 2.4
Name: hebra
Version: 0.1.0
Summary: Hebra Python SDK
Author-email: Fl0rencess <contact@swanlab.cn>
Requires-Python: >=3.12
Requires-Dist: grpcio-tools>=1.76.0
Requires-Dist: grpcio>=1.76.0
